modulusDL/__init__.py
modulusDL/eq/__init__.py
modulusDL/eq/coordinate_transformed_pde.py
modulusDL/eq/pde.py
modulusDL/geometry/__init__.py
modulusDL/geometry/geometry.py
modulusDL/geometry/ideal_encoding.py
modulusDL/geometry/ideal_warping.py
modulusDL/loss/__init__.py
modulusDL/loss/loss.py
modulusDL/models/__init__.py
modulusDL/models/arch.py
modulusDL/models/archCombi.py
modulusDL/models/layers/__init__.py
modulusDL/models/layers/inherited.py
modulusDL/solver/__init__.py
modulusDL/solver/solver.py
ModulusVascularFlow-1.0.3.dist-info/LICENSE
ModulusVascularFlow-1.0.3.dist-info/METADATA
ModulusVascularFlow-1.0.3.dist-info/WHEEL
ModulusVascularFlow-1.0.3.dist-info/top_level.txt
ModulusVascularFlow-1.0.3.dist-info/RECORD
