Metadata-Version: 2.1
Name: ModulusVascularFlow
Version: 1.0.3
Summary: Codes extention from NVIDIA Modulus.
Author-email: Wei Xuan Chan <w.x.chan1986@gmail.com>
License: MIT License
Project-URL: Homepage, https://github.com/WeiXuanChan/ModulusVascularFlow
Keywords: Modulus,pytorch,PINN
Classifier: License :: OSI Approved :: MIT License
Classifier: Programming Language :: Python
Classifier: Programming Language :: Python :: 3
Requires-Python: >=3.8
License-File: LICENSE
Provides-Extra: dev
Requires-Dist: modulus ; extra == 'dev'
